nomad_camels_toolbox/__init__.py
nomad_camels_toolbox/__main__.py
nomad_camels_toolbox/data_reader.py
nomad_camels_toolbox/graphics/CAMELS_Icon.png
nomad_camels_toolbox/plotting.py
nomad_camels_toolbox/qt_viewer.py
nomad_camels_toolbox/utils/__init__.py
nomad_camels_toolbox/utils/exception_hook.py
nomad_camels_toolbox/utils/fit_variable_renaming.py
nomad_camels_toolbox/utils/string_evaluation.py
nomad_camels_toolbox-0.3.2.dist-info/entry_points.txt
nomad_camels_toolbox-0.3.2.dist-info/LICENSE
nomad_camels_toolbox-0.3.2.dist-info/METADATA
nomad_camels_toolbox-0.3.2.dist-info/WHEEL
nomad_camels_toolbox-0.3.2.dist-info/RECORD
