Metadata-Version: 2.3
Name: nomad-camels-toolbox
Version: 0.3.2
Summary: This package provides easy access to data generated with nomad-camels
Author: nomad-camels team
Author-email: nomad-camels@fau.de
Requires-Python: >=3.10
Classifier: Programming Language :: Python :: 3
Classifier: Programming Language :: Python :: 3.10
Classifier: Programming Language :: Python :: 3.11
Classifier: Programming Language :: Python :: 3.12
Classifier: Programming Language :: Python :: 3.13
Provides-Extra: all
Provides-Extra: pandas
Provides-Extra: plotly
Provides-Extra: qt
Requires-Dist: PySide6 (>=6.6.0) ; extra == "all"
Requires-Dist: PySide6 (>=6.6.0) ; extra == "qt"
Requires-Dist: h5py (>=3.11.0,<4.0.0)
Requires-Dist: lmfit (>=0.1.2) ; extra == "all"
Requires-Dist: lmfit (>=0.1.2) ; extra == "plotly"
Requires-Dist: pandas (>=2.2.3,<3.0.0) ; extra == "all"
Requires-Dist: pandas (>=2.2.3,<3.0.0) ; extra == "pandas"
Requires-Dist: pandas (>=2.2.3,<3.0.0) ; extra == "plotly"
Requires-Dist: plotly (>=5.15.0) ; extra == "all"
Requires-Dist: plotly (>=5.15.0) ; extra == "plotly"
Requires-Dist: pyqtgraph (>=0.13.3) ; extra == "all"
Requires-Dist: pyqtgraph (>=0.13.3) ; extra == "qt"
